README.md
setup.cfg
setup.py
test_distributions_upload123/Binomialdistribution.py
test_distributions_upload123/Gaussiandistribution.py
test_distributions_upload123/Generaldistribution.py
test_distributions_upload123/__init__.py
test_distributions_upload123.egg-info/PKG-INFO
test_distributions_upload123.egg-info/SOURCES.txt
test_distributions_upload123.egg-info/dependency_links.txt
test_distributions_upload123.egg-info/not-zip-safe
test_distributions_upload123.egg-info/top_level.txt