Metadata-Version: 1.0
Name: test-distributions-upload123
Version: 0.2
Summary: Gaussian distributions
Home-page: UNKNOWN
Author: Wing Mai
Author-email: wxm19071@gmail.com
License: UNKNOWN
Platform: UNKNOWN
